easyb/__init__.py
easyb/bit.py
easyb/command.py
easyb/config.py
easyb/console.py
easyb/definitions.py
easyb/device.py
easyb/logging.py
easyb/data/__init__.py
easyb/data/base.py
easyb/data/excel.py
easyb/data/text.py
easyb/devices/__init__.py
easyb/devices/gmh3710.py
easyb/message/__init__.py
easyb/message/stream.py
easyb-0.1.0.1.data/scripts/easyb-tool.py
easyb-0.1.0.1.dist-info/LICENSE
easyb-0.1.0.1.dist-info/METADATA
easyb-0.1.0.1.dist-info/WHEEL
easyb-0.1.0.1.dist-info/top_level.txt
easyb-0.1.0.1.dist-info/RECORD
