Metadata-Version: 2.1
Name: easyb
Version: 0.1.0.1
Summary: Python tools for EASYBus Sensor modules from GMH Messtechnik GmbH
Home-page: https://github.com/TheUncleKai/pyeasyb
Author: Kai Raphahn
Author-email: kai.raphahn@laburec.de
License: Apache License, Version 2.0
Platform: UNKNOWN
Classifier: Intended Audience :: Developers
Classifier: Topic :: Other/Nonlisted Topic
Classifier: License :: OSI Approved :: Apache Software License
Classifier: Operating System :: OS Independent
Requires-Dist: colorama
Requires-Dist: pyserial
